s4/__init__.py
s4/clarity/__init__.py
s4/clarity/artifact.py
s4/clarity/console.py
s4/clarity/container.py
s4/clarity/control_type.py
s4/clarity/exception.py
s4/clarity/file.py
s4/clarity/instrument.py
s4/clarity/iomaps.py
s4/clarity/lab.py
s4/clarity/lims.py
s4/clarity/permission.py
s4/clarity/process.py
s4/clarity/project.py
s4/clarity/queue.py
s4/clarity/reagent_kit.py
s4/clarity/reagent_lot.py
s4/clarity/reagent_type.py
s4/clarity/researcher.py
s4/clarity/role.py
s4/clarity/routing.py
s4/clarity/sample.py
s4/clarity/step.py
s4/clarity/types.py
s4/clarity/version.py
s4/clarity/_internal/__init__.py
s4/clarity/_internal/element.py
s4/clarity/_internal/factory.py
s4/clarity/_internal/fakesession.py
s4/clarity/_internal/fields.py
s4/clarity/_internal/lazy_property.py
s4/clarity/_internal/props.py
s4/clarity/_internal/stepfactory.py
s4/clarity/_internal/udffactory.py
s4/clarity/configuration/__init__.py
s4/clarity/configuration/instrument_type.py
s4/clarity/configuration/process_type.py
s4/clarity/configuration/protocol.py
s4/clarity/configuration/stage.py
s4/clarity/configuration/udf.py
s4/clarity/configuration/workflow.py
s4/clarity/scripts/__init__.py
s4/clarity/scripts/derived_sample_automation.py
s4/clarity/scripts/epp_output_formatter.py
s4/clarity/scripts/file_argument_script.py
s4/clarity/scripts/genericscript.py
s4/clarity/scripts/htmllogging.py
s4/clarity/scripts/shell.py
s4/clarity/scripts/stepepp.py
s4/clarity/scripts/triggered_step_epp.py
s4/clarity/scripts/user_message_exception.py
s4/clarity/scripts/workflow_test.py
s4/clarity/steputils/__init__.py
s4/clarity/steputils/actions.py
s4/clarity/steputils/copyudfs.py
s4/clarity/steputils/file_utils.py
s4/clarity/steputils/placement_utils.py
s4/clarity/steputils/step_average_utils.py
s4/clarity/steputils/step_runner.py
s4/clarity/utils/__init__.py
s4/clarity/utils/artifact_ancestry.py
s4/clarity/utils/date_util.py
s4/clarity/utils/sorting_util.py
s4/clarity/utils/ssh.py
s4_clarity-1.8.0.dist-info/licenses/LICENSE
s4_clarity-1.8.0.dist-info/METADATA
s4_clarity-1.8.0.dist-info/WHEEL
s4_clarity-1.8.0.dist-info/top_level.txt
s4_clarity-1.8.0.dist-info/RECORD
