Metadata-Version: 2.4
Name: s4-clarity
Version: 1.8.0
Summary: A general purpose library for interacting with Clarity LIMS
Home-page: https://github.com/SemaphoreSolutions/s4-clarity-lib
Author: Semaphore Solutions
Author-email: info@semaphoresolutions.ca
Project-URL: Documentation, https://readthedocs.org/projects/s4-clarity-lib
Project-URL: Source, https://github.com/SemaphoreSolutions/s4-clarity-lib
Classifier: License :: OSI Approved :: MIT License
Classifier: Operating System :: OS Independent
Classifier: Programming Language :: Python
Classifier: Programming Language :: Python :: 2
Classifier: Programming Language :: Python :: 2.7
Classifier: Programming Language :: Python :: 3
Classifier: Programming Language :: Python :: 3.5
Classifier: Programming Language :: Python :: 3.6
Classifier: Programming Language :: Python :: 3.7
Classifier: Programming Language :: Python :: 3.8
Classifier: Programming Language :: Python :: 3.9
Classifier: Programming Language :: Python :: 3.10
Classifier: Programming Language :: Python :: 3.11
Classifier: Programming Language :: Python :: 3.12
Classifier: Programming Language :: Python :: 3.13
Classifier: Programming Language :: Python :: 3.14
Classifier: Programming Language :: Python :: Implementation :: PyPy
Requires-Python: >=2.7
License-File: LICENSE
Requires-Dist: requests>=2.22.0
Requires-Dist: argparse
Requires-Dist: python-dateutil
Requires-Dist: six
Requires-Dist: future
Requires-Dist: typing; python_version < "3.5"
Requires-Dist: urllib3>=1.25.2
Dynamic: author
Dynamic: author-email
Dynamic: classifier
Dynamic: description
Dynamic: description-content-type
Dynamic: home-page
Dynamic: license-file
Dynamic: project-url
Dynamic: requires-dist
Dynamic: requires-python
Dynamic: summary
